models/__init__.py
models/convnext.py
models/flexible_unet.py
models/flexible_unet_convnext.py
stardist_pkg/__init__.py
stardist_pkg/big.py
stardist_pkg/bioimageio_utils.py
stardist_pkg/matching.py
stardist_pkg/nms.py
stardist_pkg/rays3d.py
stardist_pkg/sample_patches.py
stardist_pkg/utils.py
stardist_pkg/version.py
stardist_pkg/geometry/__init__.py
stardist_pkg/geometry/geom2d.py
stardist_pkg/models/__init__.py
stardist_pkg/models/base.py
stardist_pkg/models/model2d.py
cellseg_sribd-0.0.1.dist-info/METADATA
cellseg_sribd-0.0.1.dist-info/WHEEL
cellseg_sribd-0.0.1.dist-info/top_level.txt
cellseg_sribd-0.0.1.dist-info/RECORD
