Metadata-Version: 2.1
Name: cellseg-sribd
Version: 0.0.1
Summary: segmentation model for multi-modal cells
Home-page: UNKNOWN
Author: Wei Lou
License: apache 3.0
Platform: UNKNOWN
Requires: numpy
Requires: matplotlib
